fpg/__init__.py
fpg/pgconn.py
fpg/pgdb.py
fpg-1.19.dist-info/METADATA
fpg-1.19.dist-info/WHEEL
fpg-1.19.dist-info/top_level.txt
fpg-1.19.dist-info/RECORD
