Metadata-Version: 2.1
Name: fpg
Version: 1.19
Summary: Flexible PostgreSQL Client
License: MIT
Classifier: Programming Language :: Python :: 3
Classifier: License :: OSI Approved :: MIT License
Classifier: Operating System :: OS Independent
Requires-Python: >=3.6
